cltrier_prosem/__init__.py
cltrier_prosem/__main___.py
cltrier_prosem/_config.py
cltrier_prosem/pooler.py
cltrier_prosem/_generics/__init__.py
cltrier_prosem/_generics/cli.py
cltrier_prosem/_generics/dataset.py
cltrier_prosem/_generics/util.py
cltrier_prosem/_generics/nn/__init__.py
cltrier_prosem/_generics/nn/encoder.py
cltrier_prosem/_generics/nn/mlp.py
cltrier_prosem/_generics/trainer/__init__.py
cltrier_prosem/_generics/trainer/metric.py
cltrier_prosem/_generics/trainer/progress.py
cltrier_prosem-0.4.3.dist-info/LICENSE
cltrier_prosem-0.4.3.dist-info/WHEEL
cltrier_prosem-0.4.3.dist-info/METADATA
cltrier_prosem-0.4.3.dist-info/RECORD
