Metadata-Version: 2.1
Name: cltrier_prosem
Version: 0.4.3
Summary: ProSem - Probing and Classifying Semantic Spans
Author-email: Simon Münker <muenker@uni-trier.de>
Requires-Python: >=3.10
Classifier: Development Status :: 3 - Alpha
Classifier: Intended Audience :: Developers
Classifier: License :: OSI Approved :: MIT License
Classifier: Programming Language :: Python :: 3.10
Requires-Dist: jsonlines>=4.0.0
Requires-Dist: tomli>=2.0.1
Requires-Dist: pyarrow>=13.0.0
Requires-Dist: pydantic>=2.5.2
Requires-Dist: tqdm>=4.66.1
Requires-Dist: numpy>=1.25.2
Requires-Dist: pandas>=2.1.0
Requires-Dist: torch>=2.0.1
Requires-Dist: transformers>=4.32.1
Requires-Dist: datasets>=1.16.1
Requires-Dist: matplotlib>=3.2.1
Requires-Dist: seaborn>=0.12.2
Requires-Dist: scikit-learn>=1.0.1
Project-URL: homepage, https://github.com/smnmnkr/cltrier_prosem
